<eses1>
<reg>
<codigoEspecif1>000930</codigoEspecif1>
<codigoGrupo> </codigoGrupo>
<codigoSubGrupo> </codigoSubGrupo>
<descricao>VERDE FECHADO NATURAL</descricao>
<formaCodigo>False</formaCodigo>
<formaDescricao>False</formaDescricao>
<indenpendente>False</indenpendente>
<controlaEstoque>False</controlaEstoque>
<codigoUsuarioModificacao> </codigoUsuarioModificacao>
<codigoUsuarioCriacao> </codigoUsuarioCriacao>
<dataModificacao>null</dataModificacao>
<mascara> </mascara>
<codigoSubGrupoFiltro> </codigoSubGrupoFiltro>
<usresp11> </usresp11>
<usresp12>0</usresp12>
<usresp13>null</usresp13>
</reg>
</eses1>
